{
  "info": {
    "description": "data",
    "version": "1.0",
    "year": 2025,
    "contributor": "search engine",
    "source": "augmented",
    "license": {
      "name": "Creative Commons Attribution 4.0 International",
      "url": "https://creativecommons.org/licenses/by/4.0/"
    }
  },
  "images": [
    {
      "id": 6877863188,
      "width": 224,
      "height": 224,
      "file_name": "aug_0_8243.jpg",
      "size": 10856,
      "format": "JPEG",
      "url": "",
      "hash": "",
      "status": "success"
    }
  ],
  "annotations": [
    {
      "id": 6747606188,
      "image_id": 6877863188,
      "category_id": 2792639188,
      "segmentation": [],
      "area": 50176,
      "bbox": [
        0,
        0,
        224,
        224
      ]
    }
  ],
  "categories": [
    {
      "id": 2792639188,
      "name": "Sheath Blight",
      "supercategory": "Sheath Blight"
    }
  ]
}